anamithra_code/__init__.py
anamithra_code/circle.py
anamithra_code/rectangle.py
anamithra_code-0.2.dist-info/METADATA
anamithra_code-0.2.dist-info/WHEEL
anamithra_code-0.2.dist-info/top_level.txt
anamithra_code-0.2.dist-info/RECORD
