Metadata-Version: 2.1
Name: anamithra-code
Version: 0.2
Summary: A simple Python library for calculating the area of geometric shapes.
Author: Anamithra
